{"v":"5.7.6","fr":30,"ip":0,"op":62,"w":573,"h":485,"nm":"1_1","ddd":0,"assets":[{"id":"comp_0","layers":[{"ddd":0,"ind":1,"ty":0,"nm":"labelb_4","refId":"comp_1","sr":1,"ks":{"o":{"a":0,"k":100,"ix":11},"r":{"a":0,"k":0,"ix":10},"p":{"a":0,"k":[286.5,242.5,0],"ix":2,"l":2},"a":{"a":0,"k":[286.5,242.5,0],"ix":1,"l":2},"s":{"a":0,"k":[100,100,100],"ix":6,"l":2}},"ao":0,"w":573,"h":485,"ip":0,"op":150,"st":0,"bm":0},{"ddd":0,"ind":2,"ty":0,"nm":"labelb_6","refId":"comp_1","sr":1,"ks":{"o":{"a":0,"k":100,"ix":11},"r":{"a":0,"k":0,"ix":10},"p":{"a":0,"k":[577.5,243.5,0],"ix":2,"l":2},"a":{"a":0,"k":[286.5,242.5,0],"ix":1,"l":2},"s":{"a":0,"k":[100,100,100],"ix":6,"l":2}},"ao":0,"w":573,"h":485,"ip":0,"op":150,"st":0,"bm":0},{"ddd":0,"ind":3,"ty":0,"nm":"labelb_7","refId":"comp_1","sr":1,"ks":{"o":{"a":0,"k":100,"ix":11},"r":{"a":0,"k":0,"ix":10},"p":{"a":0,"k":[723.5,243.5,0],"ix":2,"l":2},"a":{"a":0,"k":[286.5,242.5,0],"ix":1,"l":2},"s":{"a":0,"k":[100,100,100],"ix":6,"l":2}},"ao":0,"w":573,"h":485,"ip":0,"op":150,"st":0,"bm":0},{"ddd":0,"ind":4,"ty":0,"nm":"labelb_5","refId":"comp_2","sr":1,"ks":{"o":{"a":0,"k":100,"ix":11},"r":{"a":0,"k":0,"ix":10},"p":{"a":0,"k":[286.5,242.5,0],"ix":2,"l":2},"a":{"a":0,"k":[286.5,242.5,0],"ix":1,"l":2},"s":{"a":0,"k":[100,100,100],"ix":6,"l":2}},"ao":0,"w":573,"h":485,"ip":0,"op":150,"st":0,"bm":0},{"ddd":0,"ind":5,"ty":0,"nm":"labelb_1","refId":"comp_3","sr":1,"ks":{"o":{"a":0,"k":100,"ix":11},"r":{"a":0,"k":0,"ix":10},"p":{"a":0,"k":[286.5,242.5,0],"ix":2,"l":2},"a":{"a":0,"k":[286.5,242.5,0],"ix":1,"l":2},"s":{"a":0,"k":[100,100,100],"ix":6,"l":2}},"ao":0,"w":573,"h":485,"ip":0,"op":150,"st":0,"bm":0},{"ddd":0,"ind":6,"ty":0,"nm":"labelb_2","refId":"comp_4","sr":1,"ks":{"o":{"a":0,"k":100,"ix":11},"r":{"a":0,"k":0,"ix":10},"p":{"a":0,"k":[286.5,242.5,0],"ix":2,"l":2},"a":{"a":0,"k":[286.5,242.5,0],"ix":1,"l":2},"s":{"a":0,"k":[100,100,100],"ix":6,"l":2}},"ao":0,"w":573,"h":485,"ip":0,"op":150,"st":0,"bm":0},{"ddd":0,"ind":7,"ty":0,"nm":"layerb_3","refId":"comp_5","sr":1,"ks":{"o":{"a":0,"k":100,"ix":11},"r":{"a":0,"k":0,"ix":10},"p":{"a":0,"k":[286.5,242.5,0],"ix":2,"l":2},"a":{"a":0,"k":[286.5,242.5,0],"ix":1,"l":2},"s":{"a":0,"k":[100,100,100],"ix":6,"l":2}},"ao":0,"w":573,"h":485,"ip":0,"op":150,"st":0,"bm":0},{"ddd":0,"ind":8,"ty":4,"nm":"folder_7","sr":1,"ks":{"o":{"a":0,"k":100,"ix":11},"r":{"a":0,"k":0,"ix":10},"p":{"a":0,"k":[505.25,380.422,0],"ix":2,"l":2},"a":{"a":0,"k":[0,0,0],"ix":1,"l":2},"s":{"a":0,"k":[100,100,100],"ix":6,"l":2}},"ao":0,"ef":[{"ty":25,"nm":"Drop Shadow","np":8,"mn":"ADBE Drop Shadow","ix":1,"en":1,"ef":[{"ty":2,"nm":"Shadow Color","mn":"ADBE Drop Shadow-0001","ix":1,"v":{"a":0,"k":[0,0,0,1],"ix":1}},{"ty":0,"nm":"Opacity","mn":"ADBE Drop Shadow-0002","ix":2,"v":{"a":0,"k":38.25,"ix":2}},{"ty":0,"nm":"Direction","mn":"ADBE Drop Shadow-0003","ix":3,"v":{"a":0,"k":135,"ix":3}},{"ty":0,"nm":"Distance","mn":"ADBE Drop Shadow-0004","ix":4,"v":{"a":0,"k":5,"ix":4}},{"ty":0,"nm":"Softness","mn":"ADBE Drop Shadow-0005","ix":5,"v":{"a":0,"k":20,"ix":5}},{"ty":7,"nm":"Shadow Only","mn":"ADBE Drop Shadow-0006","ix":6,"v":{"a":0,"k":0,"ix":6}}]}],"shapes":[{"ty":"gr","it":[{"ind":0,"ty":"sh","ix":1,"ks":{"a":0,"k":{"i":[[0,0],[0,-3],[0,0],[-6.5,0],[-1.625,0.125],[0,3],[0,0],[3.5,0],[1.5,0],[2.875,-0.125]],"o":[[0,0],[0,3],[0,0],[6.5,0],[1.625,-0.125],[0,-3],[0,0],[-3.5,0],[-1.5,0],[-2.875,0.125]],"v":[[-61.75,-126],[-66.75,-121],[-67.25,-34.25],[-60.75,-28.5],[47.25,-28.5],[52,-34.25],[52,-107.5],[47.25,-113.5],[-16.75,-113.5],[-27.5,-125.5]],"c":true},"ix":2},"nm":"Path 1","mn":"ADBE Vector Shape - Group","hd":false},{"ty":"st","c":{"a":0,"k":[0.448797881603,0.451585441828,0.501761615276,1],"ix":3},"o":{"a":0,"k":100,"ix":4},"w":{"a":0,"k":0.2,"ix":5},"lc":1,"lj":1,"ml":4,"bm":0,"nm":"Stroke 1","mn":"ADBE Vector Graphic - Stroke","hd":false},{"ty":"fl","c":{"a":0,"k":[0.141176470588,0.149019607843,0.176470588235,1],"ix":4},"o":{"a":0,"k":100,"ix":5},"r":1,"bm":0,"nm":"Fill 1","mn":"ADBE Vector Graphic - Fill","hd":false},{"ty":"tr","p":{"a":0,"k":[0,0],"ix":2},"a":{"a":0,"k":[0,0],"ix":1},"s":{"a":0,"k":[100,100],"ix":3},"r":{"a":0,"k":0,"ix":6},"o":{"a":0,"k":100,"ix":7},"sk":{"a":0,"k":0,"ix":4},"sa":{"a":0,"k":0,"ix":5},"nm":"Transform"}],"nm":"Shape 1","np":3,"cix":2,"bm":0,"ix":1,"mn":"ADBE Vector Group","hd":false}],"ip":0,"op":150,"st":0,"bm":0},{"ddd":0,"ind":9,"ty":4,"nm":"folder_6","sr":1,"ks":{"o":{"a":0,"k":100,"ix":11},"r":{"a":0,"k":0,"ix":10},"p":{"a":0,"k":[359.875,380.422,0],"ix":2,"l":2},"a":{"a":0,"k":[0,0,0],"ix":1,"l":2},"s":{"a":0,"k":[100,100,100],"ix":6,"l":2}},"ao":0,"ef":[{"ty":25,"nm":"Drop Shadow","np":8,"mn":"ADBE Drop Shadow","ix":1,"en":1,"ef":[{"ty":2,"nm":"Shadow Color","mn":"ADBE Drop Shadow-0001","ix":1,"v":{"a":0,"k":[0,0,0,1],"ix":1}},{"ty":0,"nm":"Opacity","mn":"ADBE Drop Shadow-0002","ix":2,"v":{"a":0,"k":38.25,"ix":2}},{"ty":0,"nm":"Direction","mn":"ADBE Drop Shadow-0003","ix":3,"v":{"a":0,"k":135,"ix":3}},{"ty":0,"nm":"Distance","mn":"ADBE Drop Shadow-0004","ix":4,"v":{"a":0,"k":5,"ix":4}},{"ty":0,"nm":"Softness","mn":"ADBE Drop Shadow-0005","ix":5,"v":{"a":0,"k":20,"ix":5}},{"ty":7,"nm":"Shadow Only","mn":"ADBE Drop Shadow-0006","ix":6,"v":{"a":0,"k":0,"ix":6}}]}],"shapes":[{"ty":"gr","it":[{"ind":0,"ty":"sh","ix":1,"ks":{"a":0,"k":{"i":[[0,0],[0,-3],[0,0],[-6.5,0],[-1.625,0.125],[0,3],[0,0],[3.5,0],[1.5,0],[2.875,-0.125]],"o":[[0,0],[0,3],[0,0],[6.5,0],[1.625,-0.125],[0,-3],[0,0],[-3.5,0],[-1.5,0],[-2.875,0.125]],"v":[[-61.75,-126],[-66.75,-121],[-67.25,-34.25],[-60.75,-28.5],[47.25,-28.5],[52,-34.25],[52,-107.5],[47.25,-113.5],[-16.75,-113.5],[-27.5,-125.5]],"c":true},"ix":2},"nm":"Path 1","mn":"ADBE Vector Shape - Group","hd":false},{"ty":"st","c":{"a":0,"k":[0.448797881603,0.451585441828,0.501761615276,1],"ix":3},"o":{"a":0,"k":100,"ix":4},"w":{"a":0,"k":0.2,"ix":5},"lc":1,"lj":1,"ml":4,"bm":0,"nm":"Stroke 1","mn":"ADBE Vector Graphic - Stroke","hd":false},{"ty":"fl","c":{"a":0,"k":[0.141176470588,0.149019607843,0.176470588235,1],"ix":4},"o":{"a":0,"k":100,"ix":5},"r":1,"bm":0,"nm":"Fill 1","mn":"ADBE Vector Graphic - Fill","hd":false},{"ty":"tr","p":{"a":0,"k":[0,0],"ix":2},"a":{"a":0,"k":[0,0],"ix":1},"s":{"a":0,"k":[100,100],"ix":3},"r":{"a":0,"k":0,"ix":6},"o":{"a":0,"k":100,"ix":7},"sk":{"a":0,"k":0,"ix":4},"sa":{"a":0,"k":0,"ix":5},"nm":"Transform"}],"nm":"Shape 1","np":3,"cix":2,"bm":0,"ix":1,"mn":"ADBE Vector Group","hd":false}],"ip":0,"op":150,"st":0,"bm":0},{"ddd":0,"ind":10,"ty":4,"nm":"folder_5","sr":1,"ks":{"o":{"a":0,"k":100,"ix":11},"r":{"a":0,"k":0,"ix":10},"p":{"a":0,"k":[214,380.484,0],"ix":2,"l":2},"a":{"a":0,"k":[0,0,0],"ix":1,"l":2},"s":{"a":0,"k":[100,100,100],"ix":6,"l":2}},"ao":0,"ef":[{"ty":25,"nm":"Drop Shadow","np":8,"mn":"ADBE Drop Shadow","ix":1,"en":1,"ef":[{"ty":2,"nm":"Shadow Color","mn":"ADBE Drop Shadow-0001","ix":1,"v":{"a":0,"k":[0,0,0,1],"ix":1}},{"ty":0,"nm":"Opacity","mn":"ADBE Drop Shadow-0002","ix":2,"v":{"a":0,"k":38.25,"ix":2}},{"ty":0,"nm":"Direction","mn":"ADBE Drop Shadow-0003","ix":3,"v":{"a":0,"k":135,"ix":3}},{"ty":0,"nm":"Distance","mn":"ADBE Drop Shadow-0004","ix":4,"v":{"a":0,"k":5,"ix":4}},{"ty":0,"nm":"Softness","mn":"ADBE Drop Shadow-0005","ix":5,"v":{"a":0,"k":20,"ix":5}},{"ty":7,"nm":"Shadow Only","mn":"ADBE Drop Shadow-0006","ix":6,"v":{"a":0,"k":0,"ix":6}}]}],"shapes":[{"ty":"gr","it":[{"ind":0,"ty":"sh","ix":1,"ks":{"a":0,"k":{"i":[[0,0],[0,-3],[0,0],[-6.5,0],[-1.625,0.125],[0,3],[0,0],[3.5,0],[1.5,0],[2.125,0]],"o":[[0,0],[0,3],[0,0],[6.5,0],[1.625,-0.125],[0,-3],[0,0],[-3.5,0],[-1.5,0],[-2.878,0]],"v":[[-61.75,-126],[-66.75,-121],[-67.25,-34.25],[-60.75,-28.5],[47.25,-28.5],[52,-34.25],[52,-107.5],[47.25,-113.5],[-16.75,-113.5],[-27.625,-126.125]],"c":true},"ix":2},"nm":"Path 1","mn":"ADBE Vector Shape - Group","hd":false},{"ty":"st","c":{"a":0,"k":[0.448797881603,0.451585441828,0.501761615276,1],"ix":3},"o":{"a":0,"k":100,"ix":4},"w":{"a":0,"k":0.2,"ix":5},"lc":1,"lj":1,"ml":4,"bm":0,"nm":"Stroke 1","mn":"ADBE Vector Graphic - Stroke","hd":false},{"ty":"fl","c":{"a":0,"k":[0.141176470588,0.149019607843,0.176470588235,1],"ix":4},"o":{"a":0,"k":100,"ix":5},"r":1,"bm":0,"nm":"Fill 1","mn":"ADBE Vector Graphic - Fill","hd":false},{"ty":"tr","p":{"a":0,"k":[0,0],"ix":2},"a":{"a":0,"k":[0,0],"ix":1},"s":{"a":0,"k":[100,100],"ix":3},"r":{"a":0,"k":0,"ix":6},"o":{"a":0,"k":100,"ix":7},"sk":{"a":0,"k":0,"ix":4},"sa":{"a":0,"k":0,"ix":5},"nm":"Transform"}],"nm":"Shape 1","np":3,"cix":2,"bm":0,"ix":1,"mn":"ADBE Vector Group","hd":false}],"ip":0,"op":150,"st":0,"bm":0},{"ddd":0,"ind":11,"ty":4,"nm":"folder_4","sr":1,"ks":{"o":{"a":0,"k":100,"ix":11},"r":{"a":0,"k":0,"ix":10},"p":{"a":0,"k":[67.625,380.422,0],"ix":2,"l":2},"a":{"a":0,"k":[0,0,0],"ix":1,"l":2},"s":{"a":0,"k":[100,100,100],"ix":6,"l":2}},"ao":0,"ef":[{"ty":25,"nm":"Drop Shadow","np":8,"mn":"ADBE Drop Shadow","ix":1,"en":1,"ef":[{"ty":2,"nm":"Shadow Color","mn":"ADBE Drop Shadow-0001","ix":1,"v":{"a":0,"k":[0,0,0,1],"ix":1}},{"ty":0,"nm":"Opacity","mn":"ADBE Drop Shadow-0002","ix":2,"v":{"a":0,"k":38.25,"ix":2}},{"ty":0,"nm":"Direction","mn":"ADBE Drop Shadow-0003","ix":3,"v":{"a":0,"k":135,"ix":3}},{"ty":0,"nm":"Distance","mn":"ADBE Drop Shadow-0004","ix":4,"v":{"a":0,"k":5,"ix":4}},{"ty":0,"nm":"Softness","mn":"ADBE Drop Shadow-0005","ix":5,"v":{"a":0,"k":20,"ix":5}},{"ty":7,"nm":"Shadow Only","mn":"ADBE Drop Shadow-0006","ix":6,"v":{"a":0,"k":0,"ix":6}}]}],"shapes":[{"ty":"gr","it":[{"ind":0,"ty":"sh","ix":1,"ks":{"a":0,"k":{"i":[[0,0],[0,-3],[0,0],[-6.5,0],[-1.625,0.125],[0,3],[0,0],[3.5,0],[1.5,0],[2.875,-0.125]],"o":[[0,0],[0,3],[0,0],[6.5,0],[1.625,-0.125],[0,-3],[0,0],[-3.5,0],[-1.5,0],[-2.875,0.125]],"v":[[-61.75,-126],[-66.75,-121],[-67.25,-34.25],[-60.75,-28.5],[47.25,-28.5],[52,-34.25],[52,-107.5],[47.25,-113.5],[-16.75,-113.5],[-27.5,-125.5]],"c":true},"ix":2},"nm":"Path 1","mn":"ADBE Vector Shape - Group","hd":false},{"ty":"st","c":{"a":0,"k":[0.448797881603,0.451585441828,0.501761615276,1],"ix":3},"o":{"a":0,"k":100,"ix":4},"w":{"a":0,"k":0.2,"ix":5},"lc":1,"lj":1,"ml":4,"bm":0,"nm":"Stroke 1","mn":"ADBE Vector Graphic - Stroke","hd":false},{"ty":"fl","c":{"a":0,"k":[0.141176470588,0.149019607843,0.176470588235,1],"ix":4},"o":{"a":0,"k":100,"ix":5},"r":1,"bm":0,"nm":"Fill 1","mn":"ADBE Vector Graphic - Fill","hd":false},{"ty":"tr","p":{"a":0,"k":[0,0],"ix":2},"a":{"a":0,"k":[0,0],"ix":1},"s":{"a":0,"k":[100,100],"ix":3},"r":{"a":0,"k":0,"ix":6},"o":{"a":0,"k":100,"ix":7},"sk":{"a":0,"k":0,"ix":4},"sa":{"a":0,"k":0,"ix":5},"nm":"Transform"}],"nm":"Shape 1","np":3,"cix":2,"bm":0,"ix":1,"mn":"ADBE Vector Group","hd":false}],"ip":0,"op":150,"st":0,"bm":0},{"ddd":0,"ind":12,"ty":4,"nm":"folder_3","sr":1,"ks":{"o":{"a":0,"k":100,"ix":11},"r":{"a":0,"k":0,"ix":10},"p":{"a":0,"k":[433,242.5,0],"ix":2,"l":2},"a":{"a":0,"k":[0,0,0],"ix":1,"l":2},"s":{"a":0,"k":[100,100,100],"ix":6,"l":2}},"ao":0,"ef":[{"ty":25,"nm":"Drop Shadow","np":8,"mn":"ADBE Drop Shadow","ix":1,"en":1,"ef":[{"ty":2,"nm":"Shadow Color","mn":"ADBE Drop Shadow-0001","ix":1,"v":{"a":0,"k":[0,0,0,1],"ix":1}},{"ty":0,"nm":"Opacity","mn":"ADBE Drop Shadow-0002","ix":2,"v":{"a":0,"k":38.25,"ix":2}},{"ty":0,"nm":"Direction","mn":"ADBE Drop Shadow-0003","ix":3,"v":{"a":0,"k":135,"ix":3}},{"ty":0,"nm":"Distance","mn":"ADBE Drop Shadow-0004","ix":4,"v":{"a":0,"k":5,"ix":4}},{"ty":0,"nm":"Softness","mn":"ADBE Drop Shadow-0005","ix":5,"v":{"a":0,"k":20,"ix":5}},{"ty":7,"nm":"Shadow Only","mn":"ADBE Drop Shadow-0006","ix":6,"v":{"a":0,"k":0,"ix":6}}]}],"shapes":[{"ty":"gr","it":[{"ind":0,"ty":"sh","ix":1,"ks":{"a":0,"k":{"i":[[0,0],[0,-3],[0,0],[-6.5,0],[-1.625,0.125],[0,3],[0,0],[3.5,0],[1.5,0],[2.875,-0.125]],"o":[[0,0],[0,3],[0,0],[6.5,0],[1.625,-0.125],[0,-3],[0,0],[-3.5,0],[-1.5,0],[-2.875,0.125]],"v":[[-61.75,-126],[-66.75,-121],[-67.25,-34.25],[-60.75,-28.5],[47.25,-28.5],[52,-34.25],[52,-107.5],[47.25,-113.5],[-16.75,-113.5],[-27.5,-125.5]],"c":true},"ix":2},"nm":"Path 1","mn":"ADBE Vector Shape - Group","hd":false},{"ty":"st","c":{"a":0,"k":[0.448797881603,0.451585441828,0.501761615276,1],"ix":3},"o":{"a":0,"k":100,"ix":4},"w":{"a":0,"k":0.2,"ix":5},"lc":1,"lj":1,"ml":4,"bm":0,"nm":"Stroke 1","mn":"ADBE Vector Graphic - Stroke","hd":false},{"ty":"fl","c":{"a":0,"k":[0.141176470588,0.149019607843,0.176470588235,1],"ix":4},"o":{"a":0,"k":100,"ix":5},"r":1,"bm":0,"nm":"Fill 1","mn":"ADBE Vector Graphic - Fill","hd":false},{"ty":"tr","p":{"a":0,"k":[0,0],"ix":2},"a":{"a":0,"k":[0,0],"ix":1},"s":{"a":0,"k":[100,100],"ix":3},"r":{"a":0,"k":0,"ix":6},"o":{"a":0,"k":100,"ix":7},"sk":{"a":0,"k":0,"ix":4},"sa":{"a":0,"k":0,"ix":5},"nm":"Transform"}],"nm":"Shape 1","np":3,"cix":2,"bm":0,"ix":1,"mn":"ADBE Vector Group","hd":false}],"ip":0,"op":150,"st":0,"bm":0},{"ddd":0,"ind":13,"ty":4,"nm":"folder_2","sr":1,"ks":{"o":{"a":0,"k":100,"ix":11},"r":{"a":0,"k":0,"ix":10},"p":{"a":0,"k":[286.5,242.5,0],"ix":2,"l":2},"a":{"a":0,"k":[0,0,0],"ix":1,"l":2},"s":{"a":0,"k":[100,100,100],"ix":6,"l":2}},"ao":0,"ef":[{"ty":25,"nm":"Drop Shadow","np":8,"mn":"ADBE Drop Shadow","ix":1,"en":1,"ef":[{"ty":2,"nm":"Shadow Color","mn":"ADBE Drop Shadow-0001","ix":1,"v":{"a":0,"k":[0,0,0,1],"ix":1}},{"ty":0,"nm":"Opacity","mn":"ADBE Drop Shadow-0002","ix":2,"v":{"a":0,"k":38.25,"ix":2}},{"ty":0,"nm":"Direction","mn":"ADBE Drop Shadow-0003","ix":3,"v":{"a":0,"k":135,"ix":3}},{"ty":0,"nm":"Distance","mn":"ADBE Drop Shadow-0004","ix":4,"v":{"a":0,"k":5,"ix":4}},{"ty":0,"nm":"Softness","mn":"ADBE Drop Shadow-0005","ix":5,"v":{"a":0,"k":20,"ix":5}},{"ty":7,"nm":"Shadow Only","mn":"ADBE Drop Shadow-0006","ix":6,"v":{"a":0,"k":0,"ix":6}}]}],"shapes":[{"ty":"gr","it":[{"ind":0,"ty":"sh","ix":1,"ks":{"a":0,"k":{"i":[[0,0],[0,-3],[0,0],[-6.5,0],[-1.625,0.125],[0,3],[0,0],[3.5,0],[1.5,0],[2.875,-0.125]],"o":[[0,0],[0,3],[0,0],[6.5,0],[1.625,-0.125],[0,-3],[0,0],[-3.5,0],[-1.5,0],[-2.875,0.125]],"v":[[-61.75,-126],[-66.75,-121],[-67.25,-34.25],[-60.75,-28.5],[47.25,-28.5],[52,-34.25],[52,-107.5],[47.25,-113.5],[-16.75,-113.5],[-27.5,-125.5]],"c":true},"ix":2},"nm":"Path 1","mn":"ADBE Vector Shape - Group","hd":false},{"ty":"st","c":{"a":0,"k":[0.448797881603,0.451585441828,0.501761615276,1],"ix":3},"o":{"a":0,"k":100,"ix":4},"w":{"a":0,"k":0.2,"ix":5},"lc":1,"lj":1,"ml":4,"bm":0,"nm":"Stroke 1","mn":"ADBE Vector Graphic - Stroke","hd":false},{"ty":"fl","c":{"a":0,"k":[0.141176470588,0.149019607843,0.176470588235,1],"ix":4},"o":{"a":0,"k":100,"ix":5},"r":1,"bm":0,"nm":"Fill 1","mn":"ADBE Vector Graphic - Fill","hd":false},{"ty":"tr","p":{"a":0,"k":[0,0],"ix":2},"a":{"a":0,"k":[0,0],"ix":1},"s":{"a":0,"k":[100,100],"ix":3},"r":{"a":0,"k":0,"ix":6},"o":{"a":0,"k":100,"ix":7},"sk":{"a":0,"k":0,"ix":4},"sa":{"a":0,"k":0,"ix":5},"nm":"Transform"}],"nm":"Shape 1","np":3,"cix":2,"bm":0,"ix":1,"mn":"ADBE Vector Group","hd":false}],"ip":0,"op":150,"st":0,"bm":0},{"ddd":0,"ind":14,"ty":4,"nm":"folder_1","sr":1,"ks":{"o":{"a":0,"k":100,"ix":11},"r":{"a":0,"k":0,"ix":10},"p":{"a":0,"k":[140.5,242.5,0],"ix":2,"l":2},"a":{"a":0,"k":[0,0,0],"ix":1,"l":2},"s":{"a":0,"k":[100,100,100],"ix":6,"l":2}},"ao":0,"ef":[{"ty":25,"nm":"Drop Shadow","np":8,"mn":"ADBE Drop Shadow","ix":1,"en":1,"ef":[{"ty":2,"nm":"Shadow Color","mn":"ADBE Drop Shadow-0001","ix":1,"v":{"a":0,"k":[0,0,0,1],"ix":1}},{"ty":0,"nm":"Opacity","mn":"ADBE Drop Shadow-0002","ix":2,"v":{"a":0,"k":38.25,"ix":2}},{"ty":0,"nm":"Direction","mn":"ADBE Drop Shadow-0003","ix":3,"v":{"a":0,"k":135,"ix":3}},{"ty":0,"nm":"Distance","mn":"ADBE Drop Shadow-0004","ix":4,"v":{"a":0,"k":5,"ix":4}},{"ty":0,"nm":"Softness","mn":"ADBE Drop Shadow-0005","ix":5,"v":{"a":0,"k":20,"ix":5}},{"ty":7,"nm":"Shadow Only","mn":"ADBE Drop Shadow-0006","ix":6,"v":{"a":0,"k":0,"ix":6}}]}],"shapes":[{"ty":"gr","it":[{"ind":0,"ty":"sh","ix":1,"ks":{"a":0,"k":{"i":[[0,0],[0,-3],[0,0],[-6.5,0],[-1.625,0.125],[0,3],[0,0],[3.5,0],[1.5,0],[2.875,-0.125]],"o":[[0,0],[0,3],[0,0],[6.5,0],[1.625,-0.125],[0,-3],[0,0],[-3.5,0],[-1.5,0],[-2.875,0.125]],"v":[[-61.75,-126],[-66.75,-121],[-67.25,-34.25],[-60.75,-28.5],[47.25,-28.5],[52,-34.25],[52,-107.5],[47.25,-113.5],[-16.75,-113.5],[-27.5,-125.5]],"c":true},"ix":2},"nm":"Path 1","mn":"ADBE Vector Shape - Group","hd":false},{"ty":"st","c":{"a":0,"k":[0.448797881603,0.451585441828,0.501761615276,1],"ix":3},"o":{"a":0,"k":100,"ix":4},"w":{"a":0,"k":0.2,"ix":5},"lc":1,"lj":1,"ml":4,"bm":0,"nm":"Stroke 1","mn":"ADBE Vector Graphic - Stroke","hd":false},{"ty":"fl","c":{"a":0,"k":[0.141176470588,0.149019607843,0.176470588235,1],"ix":4},"o":{"a":0,"k":100,"ix":5},"r":1,"bm":0,"nm":"Fill 1","mn":"ADBE Vector Graphic - Fill","hd":false},{"ty":"tr","p":{"a":0,"k":[0,0],"ix":2},"a":{"a":0,"k":[0,0],"ix":1},"s":{"a":0,"k":[100,100],"ix":3},"r":{"a":0,"k":0,"ix":6},"o":{"a":0,"k":100,"ix":7},"sk":{"a":0,"k":0,"ix":4},"sa":{"a":0,"k":0,"ix":5},"nm":"Transform"}],"nm":"Shape 1","np":3,"cix":2,"bm":0,"ix":1,"mn":"ADBE Vector Group","hd":false}],"ip":0,"op":150,"st":0,"bm":0}]},{"id":"comp_1","layers":[{"ddd":0,"ind":2,"ty":4,"nm":"tree_3_gradient1","sr":1,"ks":{"o":{"a":0,"k":100,"ix":11},"r":{"a":0,"k":0,"ix":10},"p":{"a":0,"k":[95.875,386.5,0],"ix":2,"l":2},"a":{"a":0,"k":[0,0,0],"ix":1,"l":2},"s":{"a":0,"k":[15.225,100,100],"ix":6,"l":2}},"ao":0,"shapes":[{"ty":"gr","it":[{"ty":"rc","d":1,"s":{"a":0,"k":[81.636,21.527],"ix":2},"p":{"a":0,"k":[0,0],"ix":3},"r":{"a":0,"k":0,"ix":4},"nm":"Rectangle Path 1","mn":"ADBE Vector Shape - Rect","hd":false},{"ty":"gf","o":{"a":0,"k":60,"ix":10},"r":1,"bm":0,"g":{"p":3,"k":{"a":0,"k":[0,0.137,0.149,0.176,0.396,0.137,0.149,0.176,0.756,0.137,0.149,0.176,0,0,0.422,0.5,0.904,1],"ix":9}},"s":{"a":0,"k":[48.722,-0.156],"ix":5},"e":{"a":0,"k":[-15.96,0.157],"ix":6},"t":1,"nm":"Gradient Fill 1","mn":"ADBE Vector Graphic - G-Fill","hd":false},{"ty":"tr","p":{"a":0,"k":[-89.426,-67.189],"ix":2},"a":{"a":0,"k":[0,0],"ix":1},"s":{"a":0,"k":[106.501,100],"ix":3},"r":{"a":0,"k":0,"ix":6},"o":{"a":0,"k":60,"ix":7},"sk":{"a":0,"k":0,"ix":4},"sa":{"a":0,"k":0,"ix":5},"nm":"Transform"}],"nm":"Rectangle 1","np":2,"cix":2,"bm":0,"ix":1,"mn":"ADBE Vector Group","hd":false}],"ip":0,"op":150,"st":0,"bm":0},{"ddd":0,"ind":3,"ty":4,"nm":"tree_3_gradient2","sr":1,"ks":{"o":{"a":0,"k":100,"ix":11},"r":{"a":0,"k":0,"ix":10},"p":{"a":0,"k":[211.125,386.75,0],"ix":2,"l":2},"a":{"a":0,"k":[0,0,0],"ix":1,"l":2},"s":{"a":0,"k":[100,100,100],"ix":6,"l":2}},"ao":0,"shapes":[{"ty":"gr","it":[{"ty":"rc","d":1,"s":{"a":0,"k":[40.636,22.527],"ix":2},"p":{"a":0,"k":[0,0],"ix":3},"r":{"a":0,"k":0,"ix":4},"nm":"Rectangle Path 1","mn":"ADBE Vector Shape - Rect","hd":false},{"ty":"gf","o":{"a":0,"k":100,"ix":10},"r":1,"bm":0,"g":{"p":5,"k":{"a":0,"k":[0,0.137,0.149,0.176,0.205,0.231,0.247,0.29,0.409,0.325,0.345,0.404,0.65,0.231,0.247,0.29,0.836,0.137,0.149,0.176,0,1,0.201,0.7,0.401,0.4,0.611,0.7,0.82,1],"ix":9}},"s":{"a":0,"k":[0.264,10.816],"ix":5},"e":{"a":0,"k":[0.853,-15.045],"ix":6},"t":1,"nm":"Gradient Fill 1","mn":"ADBE Vector Graphic - G-Fill","hd":false},{"ty":"tr","p":{"a":0,"k":[-114.045,-67.176],"ix":2},"a":{"a":0,"k":[0,0],"ix":1},"s":{"a":0,"k":[106.501,100],"ix":3},"r":{"a":0,"k":0,"ix":6},"o":{"a":0,"k":29,"ix":7},"sk":{"a":0,"k":0,"ix":4},"sa":{"a":0,"k":0,"ix":5},"nm":"Transform"}],"nm":"Rectangle 1","np":2,"cix":2,"bm":0,"ix":1,"mn":"ADBE Vector Group","hd":false}],"ip":0,"op":150,"st":0,"bm":0}]},{"id":"comp_2","layers":[{"ddd":0,"ind":2,"ty":4,"nm":"tree_3_gradient1","sr":1,"ks":{"o":{"a":0,"k":100,"ix":11},"r":{"a":0,"k":0,"ix":10},"p":{"a":0,"k":[242.875,386.5,0],"ix":2,"l":2},"a":{"a":0,"k":[0,0,0],"ix":1,"l":2},"s":{"a":0,"k":[15.225,100,100],"ix":6,"l":2}},"ao":0,"shapes":[{"ty":"gr","it":[{"ty":"rc","d":1,"s":{"a":0,"k":[81.636,21.527],"ix":2},"p":{"a":0,"k":[0,0],"ix":3},"r":{"a":0,"k":0,"ix":4},"nm":"Rectangle Path 1","mn":"ADBE Vector Shape - Rect","hd":false},{"ty":"gf","o":{"a":0,"k":60,"ix":10},"r":1,"bm":0,"g":{"p":3,"k":{"a":0,"k":[0,0.137,0.149,0.176,0.396,0.137,0.149,0.176,0.756,0.137,0.149,0.176,0,0,0.422,0.5,0.904,1],"ix":9}},"s":{"a":0,"k":[48.722,-0.156],"ix":5},"e":{"a":0,"k":[-15.96,0.157],"ix":6},"t":1,"nm":"Gradient Fill 1","mn":"ADBE Vector Graphic - G-Fill","hd":false},{"ty":"tr","p":{"a":0,"k":[-89.426,-67.189],"ix":2},"a":{"a":0,"k":[0,0],"ix":1},"s":{"a":0,"k":[106.501,100],"ix":3},"r":{"a":0,"k":0,"ix":6},"o":{"a":0,"k":60,"ix":7},"sk":{"a":0,"k":0,"ix":4},"sa":{"a":0,"k":0,"ix":5},"nm":"Transform"}],"nm":"Rectangle 1","np":2,"cix":2,"bm":0,"ix":1,"mn":"ADBE Vector Group","hd":false}],"ip":0,"op":150,"st":0,"bm":0},{"ddd":0,"ind":3,"ty":4,"nm":"tree_3_gradient2","sr":1,"ks":{"o":{"a":0,"k":100,"ix":11},"r":{"a":0,"k":0,"ix":10},"p":{"a":0,"k":[358.125,386.75,0],"ix":2,"l":2},"a":{"a":0,"k":[0,0,0],"ix":1,"l":2},"s":{"a":0,"k":[100,100,100],"ix":6,"l":2}},"ao":0,"shapes":[{"ty":"gr","it":[{"ty":"rc","d":1,"s":{"a":0,"k":[40.636,22.527],"ix":2},"p":{"a":0,"k":[0,0],"ix":3},"r":{"a":0,"k":0,"ix":4},"nm":"Rectangle Path 1","mn":"ADBE Vector Shape - Rect","hd":false},{"ty":"gf","o":{"a":0,"k":100,"ix":10},"r":1,"bm":0,"g":{"p":5,"k":{"a":0,"k":[0,0.137,0.149,0.176,0.205,0.31,0.247,0.431,0.409,0.482,0.345,0.686,0.65,0.31,0.247,0.431,0.836,0.137,0.149,0.176,0,1,0.201,0.7,0.401,0.4,0.611,0.7,0.82,1],"ix":9}},"s":{"a":0,"k":[0.264,10.816],"ix":5},"e":{"a":0,"k":[0.853,-15.045],"ix":6},"t":1,"nm":"Gradient Fill 1","mn":"ADBE Vector Graphic - G-Fill","hd":false},{"ty":"tr","p":{"a":0,"k":[-114.045,-67.176],"ix":2},"a":{"a":0,"k":[0,0],"ix":1},"s":{"a":0,"k":[106.501,100],"ix":3},"r":{"a":0,"k":0,"ix":6},"o":{"a":0,"k":29,"ix":7},"sk":{"a":0,"k":0,"ix":4},"sa":{"a":0,"k":0,"ix":5},"nm":"Transform"}],"nm":"Rectangle 1","np":2,"cix":2,"bm":0,"ix":1,"mn":"ADBE Vector Group","hd":false}],"ip":0,"op":150,"st":0,"bm":0}]},{"id":"comp_3","layers":[{"ddd":0,"ind":1,"ty":3,"nm":"▽ tree_3","sr":1,"ks":{"o":{"a":0,"k":100,"ix":11},"r":{"a":0,"k":0,"ix":10},"p":{"a":0,"k":[384.306,429,0],"ix":2,"l":2},"a":{"a":0,"k":[20.592,19.854,0],"ix":1,"l":2},"s":{"a":0,"k":[100,100,100],"ix":6,"l":2}},"ao":0,"ip":0,"op":150,"st":0,"bm":0},{"ddd":0,"ind":2,"ty":4,"nm":"tree_3_gradient1","parent":1,"sr":1,"ks":{"o":{"a":0,"k":100,"ix":11},"r":{"a":0,"k":0,"ix":10},"p":{"a":0,"k":[-194.838,-159.646,0],"ix":2,"l":2},"a":{"a":0,"k":[0,0,0],"ix":1,"l":2},"s":{"a":0,"k":[15.225,100,100],"ix":6,"l":2}},"ao":0,"shapes":[{"ty":"gr","it":[{"ty":"rc","d":1,"s":{"a":0,"k":[81.636,21.527],"ix":2},"p":{"a":0,"k":[0,0],"ix":3},"r":{"a":0,"k":0,"ix":4},"nm":"Rectangle Path 1","mn":"ADBE Vector Shape - Rect","hd":false},{"ty":"gf","o":{"a":0,"k":60,"ix":10},"r":1,"bm":0,"g":{"p":3,"k":{"a":0,"k":[0,0.137,0.149,0.176,0.396,0.137,0.149,0.176,0.756,0.137,0.149,0.176,0,0,0.422,0.5,0.904,1],"ix":9}},"s":{"a":0,"k":[48.722,-0.156],"ix":5},"e":{"a":0,"k":[-15.96,0.157],"ix":6},"t":1,"nm":"Gradient Fill 1","mn":"ADBE Vector Graphic - G-Fill","hd":false},{"ty":"tr","p":{"a":0,"k":[-89.426,-67.189],"ix":2},"a":{"a":0,"k":[0,0],"ix":1},"s":{"a":0,"k":[106.501,100],"ix":3},"r":{"a":0,"k":0,"ix":6},"o":{"a":0,"k":60,"ix":7},"sk":{"a":0,"k":0,"ix":4},"sa":{"a":0,"k":0,"ix":5},"nm":"Transform"}],"nm":"Rectangle 1","np":2,"cix":2,"bm":0,"ix":1,"mn":"ADBE Vector Group","hd":false}],"ip":0,"op":150,"st":0,"bm":0},{"ddd":0,"ind":3,"ty":4,"nm":"tree_3_gradient2","parent":1,"sr":1,"ks":{"o":{"a":0,"k":100,"ix":11},"r":{"a":0,"k":0,"ix":10},"p":{"a":0,"k":[-79.588,-159.396,0],"ix":2,"l":2},"a":{"a":0,"k":[0,0,0],"ix":1,"l":2},"s":{"a":0,"k":[100,100,100],"ix":6,"l":2}},"ao":0,"shapes":[{"ty":"gr","it":[{"ty":"rc","d":1,"s":{"a":0,"k":[40.636,22.527],"ix":2},"p":{"a":0,"k":[0,0],"ix":3},"r":{"a":0,"k":0,"ix":4},"nm":"Rectangle Path 1","mn":"ADBE Vector Shape - Rect","hd":false},{"ty":"gf","o":{"a":0,"k":100,"ix":10},"r":1,"bm":0,"g":{"p":5,"k":{"a":0,"k":[0,0.137,0.149,0.176,0.205,0.239,0.316,0.465,0.409,0.341,0.482,0.753,0.65,0.239,0.316,0.465,0.836,0.137,0.149,0.176,0,1,0.201,0.7,0.401,0.4,0.611,0.7,0.82,1],"ix":9}},"s":{"a":0,"k":[0.264,10.816],"ix":5},"e":{"a":0,"k":[0.853,-15.045],"ix":6},"t":1,"nm":"Gradient Fill 1","mn":"ADBE Vector Graphic - G-Fill","hd":false},{"ty":"tr","p":{"a":0,"k":[-114.045,-67.176],"ix":2},"a":{"a":0,"k":[0,0],"ix":1},"s":{"a":0,"k":[106.501,100],"ix":3},"r":{"a":0,"k":0,"ix":6},"o":{"a":0,"k":29,"ix":7},"sk":{"a":0,"k":0,"ix":4},"sa":{"a":0,"k":0,"ix":5},"nm":"Transform"}],"nm":"Rectangle 1","np":2,"cix":2,"bm":0,"ix":1,"mn":"ADBE Vector Group","hd":false}],"ip":0,"op":150,"st":0,"bm":0}]},{"id":"comp_4","layers":[{"ddd":0,"ind":1,"ty":3,"nm":"▽ tree_3","sr":1,"ks":{"o":{"a":0,"k":100,"ix":11},"r":{"a":0,"k":0,"ix":10},"p":{"a":0,"k":[384.306,429,0],"ix":2,"l":2},"a":{"a":0,"k":[20.592,19.854,0],"ix":1,"l":2},"s":{"a":0,"k":[100,100,100],"ix":6,"l":2}},"ao":0,"ip":0,"op":150,"st":0,"bm":0},{"ddd":0,"ind":2,"ty":4,"nm":"tree_3_gradient1","parent":1,"sr":1,"ks":{"o":{"a":0,"k":100,"ix":11},"r":{"a":0,"k":0,"ix":10},"p":{"a":0,"k":[67.412,-159.396,0],"ix":2,"l":2},"a":{"a":0,"k":[0,0,0],"ix":1,"l":2},"s":{"a":0,"k":[100,100,100],"ix":6,"l":2}},"ao":0,"shapes":[{"ty":"gr","it":[{"ty":"rc","d":1,"s":{"a":0,"k":[40.636,22.527],"ix":2},"p":{"a":0,"k":[0,0],"ix":3},"r":{"a":0,"k":0,"ix":4},"nm":"Rectangle Path 1","mn":"ADBE Vector Shape - Rect","hd":false},{"ty":"gf","o":{"a":0,"k":100,"ix":10},"r":1,"bm":0,"g":{"p":3,"k":{"a":0,"k":[0,0.137,0.149,0.176,0.396,0.137,0.149,0.176,0.756,0.137,0.149,0.176,0,0,0.422,0.5,0.904,1],"ix":9}},"s":{"a":0,"k":[0.264,10.816],"ix":5},"e":{"a":0,"k":[0.853,-15.045],"ix":6},"t":1,"nm":"Gradient Fill 1","mn":"ADBE Vector Graphic - G-Fill","hd":false},{"ty":"tr","p":{"a":0,"k":[-114.045,-67.176],"ix":2},"a":{"a":0,"k":[0,0],"ix":1},"s":{"a":0,"k":[106.501,100],"ix":3},"r":{"a":0,"k":0,"ix":6},"o":{"a":0,"k":29,"ix":7},"sk":{"a":0,"k":0,"ix":4},"sa":{"a":0,"k":0,"ix":5},"nm":"Transform"}],"nm":"Rectangle 1","np":2,"cix":2,"bm":0,"ix":1,"mn":"ADBE Vector Group","hd":false}],"ip":0,"op":150,"st":0,"bm":0},{"ddd":0,"ind":3,"ty":4,"nm":"tree_3_gradient2","parent":1,"sr":1,"ks":{"o":{"a":0,"k":100,"ix":11},"r":{"a":0,"k":0,"ix":10},"p":{"a":0,"k":[-47.838,-159.646,0],"ix":2,"l":2},"a":{"a":0,"k":[0,0,0],"ix":1,"l":2},"s":{"a":0,"k":[15.225,100,100],"ix":6,"l":2}},"ao":0,"shapes":[{"ty":"gr","it":[{"ty":"rc","d":1,"s":{"a":0,"k":[81.636,21.527],"ix":2},"p":{"a":0,"k":[0,0],"ix":3},"r":{"a":0,"k":0,"ix":4},"nm":"Rectangle Path 1","mn":"ADBE Vector Shape - Rect","hd":false},{"ty":"gf","o":{"a":0,"k":60,"ix":10},"r":1,"bm":0,"g":{"p":5,"k":{"a":0,"k":[0,0.137,0.149,0.176,0.205,0.231,0.247,0.29,0.409,0.325,0.345,0.404,0.65,0.231,0.247,0.29,0.836,0.137,0.149,0.176,0,1,0.201,0.7,0.401,0.4,0.611,0.7,0.82,1],"ix":9}},"s":{"a":0,"k":[48.722,-0.156],"ix":5},"e":{"a":0,"k":[-15.96,0.157],"ix":6},"t":1,"nm":"Gradient Fill 1","mn":"ADBE Vector Graphic - G-Fill","hd":false},{"ty":"tr","p":{"a":0,"k":[-89.426,-67.189],"ix":2},"a":{"a":0,"k":[0,0],"ix":1},"s":{"a":0,"k":[106.501,100],"ix":3},"r":{"a":0,"k":0,"ix":6},"o":{"a":0,"k":60,"ix":7},"sk":{"a":0,"k":0,"ix":4},"sa":{"a":0,"k":0,"ix":5},"nm":"Transform"}],"nm":"Rectangle 1","np":2,"cix":2,"bm":0,"ix":1,"mn":"ADBE Vector Group","hd":false}],"ip":0,"op":150,"st":0,"bm":0}]},{"id":"comp_5","layers":[{"ddd":0,"ind":1,"ty":3,"nm":"▽ tree_3","sr":1,"ks":{"o":{"a":0,"k":100,"ix":11},"r":{"a":0,"k":0,"ix":10},"p":{"a":0,"k":[384.306,429,0],"ix":2,"l":2},"a":{"a":0,"k":[20.592,19.854,0],"ix":1,"l":2},"s":{"a":0,"k":[100,100,100],"ix":6,"l":2}},"ao":0,"ip":0,"op":150,"st":0,"bm":0},{"ddd":0,"ind":2,"ty":4,"nm":"tree_3_gradient1","parent":1,"sr":1,"ks":{"o":{"a":0,"k":100,"ix":11},"r":{"a":0,"k":0,"ix":10},"p":{"a":0,"k":[97.787,-159.396,0],"ix":2,"l":2},"a":{"a":0,"k":[0,0,0],"ix":1,"l":2},"s":{"a":0,"k":[15.225,100,100],"ix":6,"l":2}},"ao":0,"shapes":[{"ty":"gr","it":[{"ty":"rc","d":1,"s":{"a":0,"k":[81.636,21.527],"ix":2},"p":{"a":0,"k":[0,0],"ix":3},"r":{"a":0,"k":0,"ix":4},"nm":"Rectangle Path 1","mn":"ADBE Vector Shape - Rect","hd":false},{"ty":"gf","o":{"a":0,"k":60,"ix":10},"r":1,"bm":0,"g":{"p":3,"k":{"a":0,"k":[0,0.137,0.149,0.176,0.396,0.137,0.149,0.176,0.756,0.137,0.149,0.176,0,0,0.422,0.5,0.904,1],"ix":9}},"s":{"a":0,"k":[48.722,-0.156],"ix":5},"e":{"a":0,"k":[-15.96,0.157],"ix":6},"t":1,"nm":"Gradient Fill 1","mn":"ADBE Vector Graphic - G-Fill","hd":false},{"ty":"tr","p":{"a":0,"k":[-89.426,-67.189],"ix":2},"a":{"a":0,"k":[0,0],"ix":1},"s":{"a":0,"k":[106.501,100],"ix":3},"r":{"a":0,"k":0,"ix":6},"o":{"a":0,"k":60,"ix":7},"sk":{"a":0,"k":0,"ix":4},"sa":{"a":0,"k":0,"ix":5},"nm":"Transform"}],"nm":"Rectangle 1","np":2,"cix":2,"bm":0,"ix":1,"mn":"ADBE Vector Group","hd":false}],"ip":0,"op":150,"st":0,"bm":0},{"ddd":0,"ind":3,"ty":4,"nm":"tree_3_gradient2","parent":1,"sr":1,"ks":{"o":{"a":0,"k":100,"ix":11},"r":{"a":0,"k":0,"ix":10},"p":{"a":0,"k":[213.037,-159.146,0],"ix":2,"l":2},"a":{"a":0,"k":[0,0,0],"ix":1,"l":2},"s":{"a":0,"k":[100,100,100],"ix":6,"l":2}},"ao":0,"shapes":[{"ty":"gr","it":[{"ty":"rc","d":1,"s":{"a":0,"k":[40.636,22.527],"ix":2},"p":{"a":0,"k":[0,0],"ix":3},"r":{"a":0,"k":0,"ix":4},"nm":"Rectangle Path 1","mn":"ADBE Vector Shape - Rect","hd":false},{"ty":"gf","o":{"a":0,"k":100,"ix":10},"r":1,"bm":0,"g":{"p":5,"k":{"a":0,"k":[0,0.137,0.149,0.176,0.205,0.229,0.475,0.488,0.409,0.322,0.8,0.8,0.65,0.229,0.475,0.488,0.836,0.137,0.149,0.176,0,1,0.201,0.7,0.401,0.4,0.611,0.7,0.82,1],"ix":9}},"s":{"a":0,"k":[0.264,10.816],"ix":5},"e":{"a":0,"k":[0.853,-15.045],"ix":6},"t":1,"nm":"Gradient Fill 1","mn":"ADBE Vector Graphic - G-Fill","hd":false},{"ty":"tr","p":{"a":0,"k":[-114.045,-67.176],"ix":2},"a":{"a":0,"k":[0,0],"ix":1},"s":{"a":0,"k":[106.501,100],"ix":3},"r":{"a":0,"k":0,"ix":6},"o":{"a":0,"k":29,"ix":7},"sk":{"a":0,"k":0,"ix":4},"sa":{"a":0,"k":0,"ix":5},"nm":"Transform"}],"nm":"Rectangle 1","np":2,"cix":2,"bm":0,"ix":1,"mn":"ADBE Vector Group","hd":false}],"ip":0,"op":150,"st":0,"bm":0}]},{"id":"comp_6","layers":[{"ddd":0,"ind":1,"ty":3,"nm":"tree_3","sr":1,"ks":{"o":{"a":0,"k":100,"ix":11},"r":{"a":0,"k":0,"ix":10},"p":{"a":0,"k":[286.5,234,0],"ix":2,"l":2},"a":{"a":0,"k":[286.5,118,0],"ix":1,"l":2},"s":{"a":0,"k":[100,100,100],"ix":6,"l":2}},"ao":0,"ip":0,"op":150,"st":0,"bm":0},{"ddd":0,"ind":2,"ty":4,"nm":"tree_3_gradient","parent":1,"sr":1,"ks":{"o":{"a":0,"k":100,"ix":11},"r":{"a":0,"k":0,"ix":10},"p":{"a":0,"k":[286.5,126.5,0],"ix":2,"l":2},"a":{"a":0,"k":[0,0,0],"ix":1,"l":2},"s":{"a":0,"k":[100,100,100],"ix":6,"l":2}},"ao":0,"ef":[{"ty":25,"nm":"Drop Shadow","np":8,"mn":"ADBE Drop Shadow","ix":1,"en":1,"ef":[{"ty":2,"nm":"Shadow Color","mn":"ADBE Drop Shadow-0001","ix":1,"v":{"a":0,"k":[0,0,0,1],"ix":1}},{"ty":0,"nm":"Opacity","mn":"ADBE Drop Shadow-0002","ix":2,"v":{"a":0,"k":20.4,"ix":2}},{"ty":0,"nm":"Direction","mn":"ADBE Drop Shadow-0003","ix":3,"v":{"a":0,"k":135,"ix":3}},{"ty":0,"nm":"Distance","mn":"ADBE Drop Shadow-0004","ix":4,"v":{"a":0,"k":12,"ix":4}},{"ty":0,"nm":"Softness","mn":"ADBE Drop Shadow-0005","ix":5,"v":{"a":0,"k":20,"ix":5}},{"ty":7,"nm":"Shadow Only","mn":"ADBE Drop Shadow-0006","ix":6,"v":{"a":0,"k":0,"ix":6}}]}],"shapes":[{"ty":"gr","it":[{"ind":0,"ty":"sh","ix":1,"ks":{"a":0,"k":{"i":[[1.625,0],[-1.625,-0.5],[-1.625,0],[1.25,0],[0.75,0]],"o":[[-1.625,0],[1.75,0],[1.625,0],[-1.25,0],[-0.75,0]],"v":[[-15.625,2.125],[-38.75,35.875],[21.625,35.875],[6.25,12.25],[-0.625,22.625]],"c":true},"ix":2},"nm":"Path 1","mn":"ADBE Vector Shape - Group","hd":false},{"ty":"st","c":{"a":0,"k":[0.301102936268,0.316544115543,0.370588243008,1],"ix":3},"o":{"a":0,"k":100,"ix":4},"w":{"a":0,"k":0.4,"ix":5},"lc":1,"lj":1,"ml":4,"bm":0,"nm":"Stroke 1","mn":"ADBE Vector Graphic - Stroke","hd":false},{"ty":"gf","o":{"a":0,"k":100,"ix":10},"r":1,"bm":0,"g":{"p":3,"k":{"a":0,"k":[0,0.257,0.271,0.317,0.254,0.216,0.229,0.265,0.933,0.175,0.188,0.214,0,0.7,0.468,0.85,0.936,1],"ix":9}},"s":{"a":0,"k":[-2.859,31.454],"ix":5},"e":{"a":0,"k":[-2.206,20.001],"ix":6},"t":1,"nm":"Gradient Fill 1","mn":"ADBE Vector Graphic - G-Fill","hd":false},{"ty":"tr","p":{"a":0,"k":[0.035,-0.852],"ix":2},"a":{"a":0,"k":[0,0],"ix":1},"s":{"a":0,"k":[100,100],"ix":3},"r":{"a":0,"k":0,"ix":6},"o":{"a":0,"k":100,"ix":7},"sk":{"a":0,"k":0,"ix":4},"sa":{"a":0,"k":0,"ix":5},"nm":"Transform"}],"nm":"Shape 1","np":3,"cix":2,"bm":0,"ix":1,"mn":"ADBE Vector Group","hd":false}],"ip":0,"op":150,"st":0,"bm":0},{"ddd":0,"ind":3,"ty":0,"nm":"스크린샷 작업중","refId":"comp_7","sr":1,"ks":{"o":{"a":0,"k":100,"ix":11},"r":{"a":0,"k":0,"ix":10},"p":{"a":0,"k":[287,256.5,0],"ix":2,"l":2},"a":{"a":0,"k":[98,181.5,0],"ix":1,"l":2},"s":{"a":0,"k":[100,100,100],"ix":6,"l":2}},"ao":0,"w":196,"h":363,"ip":0,"op":150,"st":0,"bm":0},{"ddd":0,"ind":4,"ty":3,"nm":"tree_4","sr":1,"ks":{"o":{"a":0,"k":100,"ix":11},"r":{"a":0,"k":0,"ix":10},"p":{"a":0,"k":[286.5,234,0],"ix":2,"l":2},"a":{"a":0,"k":[286.5,118,0],"ix":1,"l":2},"s":{"a":0,"k":[100,100,100],"ix":6,"l":2}},"ao":0,"ip":0,"op":150,"st":0,"bm":0},{"ddd":0,"ind":5,"ty":4,"nm":"Rectangle 928","parent":4,"sr":1,"ks":{"o":{"a":0,"k":100,"ix":11},"r":{"a":0,"k":-15,"ix":10},"p":{"a":0,"k":[84.625,252.347,0],"ix":2,"l":2},"a":{"a":0,"k":[0,0,0],"ix":1,"l":2},"s":{"a":0,"k":[100,100,100],"ix":6,"l":2}},"ao":0,"shapes":[{"ty":"gr","it":[{"ty":"rc","d":1,"s":{"a":0,"k":[117,209.552],"ix":2},"p":{"a":0,"k":[0,0],"ix":3},"r":{"a":0,"k":0,"ix":4},"nm":"Rectangle Path 1","mn":"ADBE Vector Shape - Rect","hd":false},{"ty":"fl","c":{"a":0,"k":[0.129411771894,0.133333340287,0.156862750649,1],"ix":4},"o":{"a":0,"k":100,"ix":5},"r":1,"bm":0,"nm":"Fill 1","mn":"ADBE Vector Graphic - Fill","hd":false},{"ty":"tr","p":{"a":0,"k":[0,0],"ix":2},"a":{"a":0,"k":[0,0],"ix":1},"s":{"a":0,"k":[100,100],"ix":3},"r":{"a":1,"k":[{"i":{"x":[0.833],"y":[0.833]},"o":{"x":[0.167],"y":[0.167]},"t":0,"s":[30]},{"t":9,"s":[15]}],"ix":6},"o":{"a":0,"k":100,"ix":7},"sk":{"a":0,"k":0,"ix":4},"sa":{"a":0,"k":0,"ix":5},"nm":"Transform"}],"nm":"Rectangle 928","np":2,"cix":2,"bm":0,"ix":1,"mn":"ADBE Vector Group","hd":false}],"ip":0,"op":150,"st":0,"bm":0},{"ddd":0,"ind":6,"ty":4,"nm":"Rectangle 927","parent":4,"sr":1,"ks":{"o":{"a":0,"k":100,"ix":11},"r":{"a":1,"k":[{"i":{"x":[0.833],"y":[0.833]},"o":{"x":[0.167],"y":[0.167]},"t":0,"s":[0]},{"t":9,"s":[15]}],"ix":10},"p":{"a":0,"k":[489.085,0.988,0],"ix":2,"l":2},"a":{"a":0,"k":[0,0,0],"ix":1,"l":2},"s":{"a":0,"k":[100,100,100],"ix":6,"l":2}},"ao":0,"shapes":[{"ty":"gr","it":[{"ty":"rc","d":1,"s":{"a":0,"k":[117.644,210.706],"ix":2},"p":{"a":0,"k":[0,0],"ix":3},"r":{"a":0,"k":0,"ix":4},"nm":"Rectangle Path 1","mn":"ADBE Vector Shape - Rect","hd":false},{"ty":"fl","c":{"a":0,"k":[0.129411771894,0.133333340287,0.156862750649,1],"ix":4},"o":{"a":0,"k":100,"ix":5},"r":1,"bm":0,"nm":"Fill 1","mn":"ADBE Vector Graphic - Fill","hd":false},{"ty":"tr","p":{"a":0,"k":[0,0],"ix":2},"a":{"a":0,"k":[0,0],"ix":1},"s":{"a":0,"k":[100,100],"ix":3},"r":{"a":0,"k":-15,"ix":6},"o":{"a":0,"k":100,"ix":7},"sk":{"a":0,"k":0,"ix":4},"sa":{"a":0,"k":0,"ix":5},"nm":"Transform"}],"nm":"Rectangle 927","np":2,"cix":2,"bm":0,"ix":1,"mn":"ADBE Vector Group","hd":false}],"ip":0,"op":150,"st":0,"bm":0}]},{"id":"comp_7","layers":[{"ddd":0,"ind":1,"ty":3,"nm":"▽ Group 548","sr":1,"ks":{"o":{"a":0,"k":100,"ix":11},"r":{"a":0,"k":0,"ix":10},"p":{"a":0,"k":[97.213,176,0],"ix":2,"l":2},"a":{"a":0,"k":[37.213,28,0],"ix":1,"l":2},"s":{"a":0,"k":[100,100,100],"ix":6,"l":2}},"ao":0,"ip":0,"op":150,"st":0,"bm":0},{"ddd":0,"ind":2,"ty":4,"nm":"Rectangle 933","parent":1,"sr":1,"ks":{"o":{"a":0,"k":100,"ix":11},"r":{"a":0,"k":0,"ix":10},"p":{"a":0,"k":[58.426,16,0],"ix":2,"l":2},"a":{"a":0,"k":[0,0,0],"ix":1,"l":2},"s":{"a":0,"k":[100,100,100],"ix":6,"l":2}},"ao":0,"shapes":[{"ty":"gr","it":[{"ty":"rc","d":1,"s":{"a":0,"k":[12,12],"ix":2},"p":{"a":0,"k":[0,0],"ix":3},"r":{"a":0,"k":50,"ix":4},"nm":"Rectangle Path 1","mn":"ADBE Vector Shape - Rect","hd":false},{"ty":"fl","c":{"a":0,"k":[0.160784319043,0.172549024224,0.20000000298,1],"ix":4},"o":{"a":0,"k":100,"ix":5},"r":1,"bm":0,"nm":"Fill 1","mn":"ADBE Vector Graphic - Fill","hd":false},{"ty":"tr","p":{"a":0,"k":[0,0],"ix":2},"a":{"a":0,"k":[0,0],"ix":1},"s":{"a":0,"k":[100,100],"ix":3},"r":{"a":0,"k":0,"ix":6},"o":{"a":0,"k":100,"ix":7},"sk":{"a":0,"k":0,"ix":4},"sa":{"a":0,"k":0,"ix":5},"nm":"Transform"}],"nm":"Rectangle 933","np":2,"cix":2,"bm":0,"ix":1,"mn":"ADBE Vector Group","hd":false}],"ip":0,"op":150,"st":0,"bm":0},{"ddd":0,"ind":3,"ty":4,"nm":"Rectangle 938","parent":1,"sr":1,"ks":{"o":{"a":0,"k":100,"ix":11},"r":{"a":0,"k":0,"ix":10},"p":{"a":0,"k":[40.426,25,0],"ix":2,"l":2},"a":{"a":0,"k":[0,0,0],"ix":1,"l":2},"s":{"a":0,"k":[100,100,100],"ix":6,"l":2}},"ao":0,"shapes":[{"ty":"gr","it":[{"ty":"rc","d":1,"s":{"a":0,"k":[68,50],"ix":2},"p":{"a":0,"k":[0,0],"ix":3},"r":{"a":0,"k":2,"ix":4},"nm":"Rectangle Path 1","mn":"ADBE Vector Shape - Rect","hd":false},{"ty":"fl","c":{"a":0,"k":[0.103999994695,0.111799992621,0.129999995232,1],"ix":4},"o":{"a":0,"k":100,"ix":5},"r":1,"bm":0,"nm":"Fill 1","mn":"ADBE Vector Graphic - Fill","hd":false},{"ty":"tr","p":{"a":0,"k":[0,0],"ix":2},"a":{"a":0,"k":[0,0],"ix":1},"s":{"a":0,"k":[100,100],"ix":3},"r":{"a":0,"k":0,"ix":6},"o":{"a":0,"k":100,"ix":7},"sk":{"a":0,"k":0,"ix":4},"sa":{"a":0,"k":0,"ix":5},"nm":"Transform"}],"nm":"Rectangle 938","np":2,"cix":2,"bm":0,"ix":1,"mn":"ADBE Vector Group","hd":false}],"ip":0,"op":150,"st":0,"bm":0},{"ddd":0,"ind":4,"ty":3,"nm":"▽ Group 535","sr":1,"ks":{"o":{"a":0,"k":100,"ix":11},"r":{"a":0,"k":0,"ix":10},"p":{"a":0,"k":[168,14.737,0],"ix":2,"l":2},"a":{"a":0,"k":[18,4.737,0],"ix":1,"l":2},"s":{"a":0,"k":[100,100,100],"ix":6,"l":2}},"ao":0,"ip":0,"op":150,"st":0,"bm":0},{"ddd":0,"ind":5,"ty":4,"nm":"Vector 165","parent":4,"sr":1,"ks":{"o":{"a":0,"k":100,"ix":11},"r":{"a":0,"k":0,"ix":10},"p":{"a":0,"k":[31.263,4.263,0],"ix":2,"l":2},"a":{"a":0,"k":[0,0,0],"ix":1,"l":2},"s":{"a":0,"k":[100,100,100],"ix":6,"l":2}},"ao":0,"shapes":[{"ty":"gr","it":[{"ind":0,"ty":"sh","ix":1,"ks":{"a":0,"k":{"i":[[0,0],[0,0],[0,0]],"o":[[0,0],[0,0],[0,0]],"v":[[-4.737,4.263],[0,-4.263],[4.737,4.263]],"c":true},"ix":2},"nm":"Path 1","mn":"ADBE Vector Shape - Group","hd":false},{"ty":"fl","c":{"a":0,"k":[0.29411765933,0.305882364511,0.337254911661,1],"ix":4},"o":{"a":0,"k":100,"ix":5},"r":1,"bm":0,"nm":"Fill 1","mn":"ADBE Vector Graphic - Fill","hd":false},{"ty":"tr","p":{"a":0,"k":[0,0],"ix":2},"a":{"a":0,"k":[0,0],"ix":1},"s":{"a":0,"k":[100,100],"ix":3},"r":{"a":0,"k":0,"ix":6},"o":{"a":0,"k":100,"ix":7},"sk":{"a":0,"k":0,"ix":4},"sa":{"a":0,"k":0,"ix":5},"nm":"Transform"}],"nm":"Vector 165","np":2,"cix":2,"bm":0,"ix":1,"mn":"ADBE Vector Group","hd":false}],"ip":0,"op":150,"st":0,"bm":0},{"ddd":0,"ind":6,"ty":4,"nm":"Rectangle 925","parent":4,"sr":1,"ks":{"o":{"a":0,"k":100,"ix":11},"r":{"a":0,"k":0,"ix":10},"p":{"a":0,"k":[4.263,4.737,0],"ix":2,"l":2},"a":{"a":0,"k":[0,0,0],"ix":1,"l":2},"s":{"a":0,"k":[100,100,100],"ix":6,"l":2}},"ao":0,"shapes":[{"ty":"gr","it":[{"ty":"rc","d":1,"s":{"a":0,"k":[8.526,8.526],"ix":2},"p":{"a":0,"k":[0,0],"ix":3},"r":{"a":0,"k":0,"ix":4},"nm":"Rectangle Path 1","mn":"ADBE Vector Shape - Rect","hd":false},{"ty":"fl","c":{"a":0,"k":[0.29411765933,0.305882364511,0.337254911661,1],"ix":4},"o":{"a":0,"k":100,"ix":5},"r":1,"bm":0,"nm":"Fill 1","mn":"ADBE Vector Graphic - Fill","hd":false},{"ty":"tr","p":{"a":0,"k":[0,0],"ix":2},"a":{"a":0,"k":[0,0],"ix":1},"s":{"a":0,"k":[100,100],"ix":3},"r":{"a":0,"k":0,"ix":6},"o":{"a":0,"k":100,"ix":7},"sk":{"a":0,"k":0,"ix":4},"sa":{"a":0,"k":0,"ix":5},"nm":"Transform"}],"nm":"Rectangle 925","np":2,"cix":2,"bm":0,"ix":1,"mn":"ADBE Vector Group","hd":false}],"ip":0,"op":150,"st":0,"bm":0},{"ddd":0,"ind":7,"ty":4,"nm":"Ellipse 196","parent":4,"sr":1,"ks":{"o":{"a":0,"k":100,"ix":11},"r":{"a":0,"k":0,"ix":10},"p":{"a":0,"k":[18,4.737,0],"ix":2,"l":2},"a":{"a":0,"k":[0,0,0],"ix":1,"l":2},"s":{"a":0,"k":[100,100,100],"ix":6,"l":2}},"ao":0,"shapes":[{"ty":"gr","it":[{"d":1,"ty":"el","s":{"a":0,"k":[9.474,9.474],"ix":2},"p":{"a":0,"k":[0,0],"ix":3},"nm":"Ellipse Path 1","mn":"ADBE Vector Shape - Ellipse","hd":false},{"ty":"fl","c":{"a":0,"k":[0.29411765933,0.305882364511,0.337254911661,1],"ix":4},"o":{"a":0,"k":100,"ix":5},"r":1,"bm":0,"nm":"Fill 1","mn":"ADBE Vector Graphic - Fill","hd":false},{"ty":"tr","p":{"a":0,"k":[0,0],"ix":2},"a":{"a":0,"k":[0,0],"ix":1},"s":{"a":0,"k":[100,100],"ix":3},"r":{"a":0,"k":0,"ix":6},"o":{"a":0,"k":100,"ix":7},"sk":{"a":0,"k":0,"ix":4},"sa":{"a":0,"k":0,"ix":5},"nm":"Transform"}],"nm":"Ellipse 196","np":2,"cix":2,"bm":0,"ix":1,"mn":"ADBE Vector Group","hd":false}],"ip":0,"op":150,"st":0,"bm":0},{"ddd":0,"ind":8,"ty":4,"nm":"Rectangle 815","sr":1,"ks":{"o":{"a":0,"k":100,"ix":11},"r":{"a":0,"k":0,"ix":10},"p":{"a":0,"k":[98,181.5,0],"ix":2,"l":2},"a":{"a":0,"k":[0,0,0],"ix":1,"l":2},"s":{"a":0,"k":[100,100,100],"ix":6,"l":2}},"ao":0,"ef":[{"ty":25,"nm":"Drop Shadow","np":8,"mn":"ADBE Drop Shadow","ix":1,"en":1,"ef":[{"ty":2,"nm":"Shadow Color","mn":"ADBE Drop Shadow-0001","ix":1,"v":{"a":0,"k":[0,0,0,1],"ix":1}},{"ty":0,"nm":"Opacity","mn":"ADBE Drop Shadow-0002","ix":2,"v":{"a":0,"k":20.4,"ix":2}},{"ty":0,"nm":"Direction","mn":"ADBE Drop Shadow-0003","ix":3,"v":{"a":0,"k":135,"ix":3}},{"ty":0,"nm":"Distance","mn":"ADBE Drop Shadow-0004","ix":4,"v":{"a":0,"k":15,"ix":4}},{"ty":0,"nm":"Softness","mn":"ADBE Drop Shadow-0005","ix":5,"v":{"a":0,"k":20,"ix":5}},{"ty":7,"nm":"Shadow Only","mn":"ADBE Drop Shadow-0006","ix":6,"v":{"a":0,"k":0,"ix":6}}]}],"shapes":[{"ty":"gr","it":[{"ty":"rc","d":1,"s":{"a":0,"k":[196,363],"ix":2},"p":{"a":0,"k":[0,0],"ix":3},"r":{"a":0,"k":2,"ix":4},"nm":"Rectangle Path 1","mn":"ADBE Vector Shape - Rect","hd":false},{"ty":"fl","c":{"a":0,"k":[0.152941182256,0.160784319043,0.188235297799,1],"ix":4},"o":{"a":0,"k":100,"ix":5},"r":1,"bm":0,"nm":"Fill 1","mn":"ADBE Vector Graphic - Fill","hd":false},{"ty":"tr","p":{"a":0,"k":[0,0],"ix":2},"a":{"a":0,"k":[0,0],"ix":1},"s":{"a":0,"k":[100,100],"ix":3},"r":{"a":0,"k":0,"ix":6},"o":{"a":0,"k":100,"ix":7},"sk":{"a":0,"k":0,"ix":4},"sa":{"a":0,"k":0,"ix":5},"nm":"Transform"}],"nm":"Rectangle 815","np":2,"cix":2,"bm":0,"ix":1,"mn":"ADBE Vector Group","hd":false}],"ip":0,"op":150,"st":0,"bm":0},{"ddd":0,"ind":9,"ty":4,"nm":"스크린샷 작업중","sr":1,"ks":{"o":{"a":0,"k":100,"ix":11},"r":{"a":0,"k":0,"ix":10},"p":{"a":0,"k":[98,181.5,0],"ix":2,"l":2},"a":{"a":0,"k":[0,0,0],"ix":1,"l":2},"s":{"a":0,"k":[100,100,100],"ix":6,"l":2}},"ao":0,"shapes":[{"ty":"gr","it":[{"ty":"rc","d":1,"s":{"a":0,"k":[196,363],"ix":2},"p":{"a":0,"k":[0,0],"ix":3},"r":{"a":0,"k":0,"ix":4},"nm":"Rectangle Path 1","mn":"ADBE Vector Shape - Rect","hd":false},{"ty":"tr","p":{"a":0,"k":[0,0],"ix":2},"a":{"a":0,"k":[0,0],"ix":1},"s":{"a":0,"k":[100,100],"ix":3},"r":{"a":0,"k":0,"ix":6},"o":{"a":0,"k":100,"ix":7},"sk":{"a":0,"k":0,"ix":4},"sa":{"a":0,"k":0,"ix":5},"nm":"Transform"}],"nm":"스크린샷 작업중","np":1,"cix":2,"bm":0,"ix":1,"mn":"ADBE Vector Group","hd":false}],"ip":0,"op":150,"st":0,"bm":0}]}],"layers":[{"ddd":0,"ind":1,"ty":0,"nm":"folder","refId":"comp_0","sr":1,"ks":{"o":{"a":1,"k":[{"i":{"x":[0.833],"y":[0.833]},"o":{"x":[0.167],"y":[0.167]},"t":31,"s":[0]},{"t":43,"s":[90]}],"ix":11},"r":{"a":0,"k":0,"ix":10},"p":{"a":0,"k":[286.5,242.5,0],"ix":2,"l":2},"a":{"a":0,"k":[286.5,242.5,0],"ix":1,"l":2},"s":{"a":0,"k":[100,100,100],"ix":6,"l":2}},"ao":0,"w":573,"h":485,"ip":30,"op":180,"st":30,"bm":0},{"ddd":0,"ind":2,"ty":4,"nm":"label04","sr":1,"ks":{"o":{"a":0,"k":100,"ix":11},"r":{"a":0,"k":0,"ix":10},"p":{"a":0,"k":[106,321,0],"ix":2,"l":2},"a":{"a":0,"k":[0,0,0],"ix":1,"l":2},"s":{"a":0,"k":[100,100,100],"ix":6,"l":2}},"ao":0,"shapes":[{"ty":"gr","it":[{"ty":"rc","d":1,"s":{"a":0,"k":[58,22],"ix":2},"p":{"a":0,"k":[0,0],"ix":3},"r":{"a":0,"k":1,"ix":4},"nm":"Rectangle Path 1","mn":"ADBE Vector Shape - Rect","hd":false},{"ty":"st","c":{"a":0,"k":[0.435294121504,0.450980395079,0.509803950787,1],"ix":3},"o":{"a":0,"k":100,"ix":4},"w":{"a":0,"k":0.5,"ix":5},"lc":1,"lj":1,"ml":4,"bm":0,"nm":"Stroke 1","mn":"ADBE Vector Graphic - Stroke","hd":false},{"ty":"fl","c":{"a":0,"k":[0.32549020648,0.345098048449,0.403921574354,1],"ix":4},"o":{"a":0,"k":100,"ix":5},"r":1,"bm":0,"nm":"Fill 1","mn":"ADBE Vector Graphic - Fill","hd":false},{"ty":"tr","p":{"a":0,"k":[0,0],"ix":2},"a":{"a":0,"k":[0,0],"ix":1},"s":{"a":0,"k":[100,100],"ix":3},"r":{"a":0,"k":0,"ix":6},"o":{"a":0,"k":100,"ix":7},"sk":{"a":0,"k":0,"ix":4},"sa":{"a":0,"k":0,"ix":5},"nm":"Transform"}],"nm":"Rectangle 9337","np":3,"cix":2,"bm":0,"ix":1,"mn":"ADBE Vector Group","hd":false}],"ip":33,"op":183,"st":33,"bm":0},{"ddd":0,"ind":3,"ty":4,"nm":"label03","sr":1,"ks":{"o":{"a":0,"k":100,"ix":11},"r":{"a":0,"k":0,"ix":10},"p":{"a":0,"k":[471,183,0],"ix":2,"l":2},"a":{"a":0,"k":[0,0,0],"ix":1,"l":2},"s":{"a":0,"k":[100,100,100],"ix":6,"l":2}},"ao":0,"shapes":[{"ty":"gr","it":[{"ty":"rc","d":1,"s":{"a":0,"k":[58,22],"ix":2},"p":{"a":0,"k":[0,0],"ix":3},"r":{"a":0,"k":1,"ix":4},"nm":"Rectangle Path 1","mn":"ADBE Vector Shape - Rect","hd":false},{"ty":"st","c":{"a":0,"k":[0.43137255311,0.823529422283,0.835294127464,1],"ix":3},"o":{"a":0,"k":100,"ix":4},"w":{"a":0,"k":0.5,"ix":5},"lc":1,"lj":1,"ml":4,"bm":0,"nm":"Stroke 1","mn":"ADBE Vector Graphic - Stroke","hd":false},{"ty":"fl","c":{"a":0,"k":[0.321568638086,0.800000011921,0.800000011921,1],"ix":4},"o":{"a":0,"k":100,"ix":5},"r":1,"bm":0,"nm":"Fill 1","mn":"ADBE Vector Graphic - Fill","hd":false},{"ty":"tr","p":{"a":0,"k":[0,0],"ix":2},"a":{"a":0,"k":[0,0],"ix":1},"s":{"a":0,"k":[100,100],"ix":3},"r":{"a":0,"k":0,"ix":6},"o":{"a":0,"k":100,"ix":7},"sk":{"a":0,"k":0,"ix":4},"sa":{"a":0,"k":0,"ix":5},"nm":"Transform"}],"nm":"Rectangle 931","np":3,"cix":2,"bm":0,"ix":1,"mn":"ADBE Vector Group","hd":false}],"ip":33,"op":183,"st":33,"bm":0},{"ddd":0,"ind":4,"ty":4,"nm":"label06","sr":1,"ks":{"o":{"a":0,"k":100,"ix":11},"r":{"a":0,"k":0,"ix":10},"p":{"a":0,"k":[398,321,0],"ix":2,"l":2},"a":{"a":0,"k":[0,0,0],"ix":1,"l":2},"s":{"a":0,"k":[100,100,100],"ix":6,"l":2}},"ao":0,"shapes":[{"ty":"gr","it":[{"ty":"rc","d":1,"s":{"a":0,"k":[58,22],"ix":2},"p":{"a":0,"k":[0,0],"ix":3},"r":{"a":0,"k":1,"ix":4},"nm":"Rectangle Path 1","mn":"ADBE Vector Shape - Rect","hd":false},{"ty":"st","c":{"a":0,"k":[0.435294121504,0.450980395079,0.509803950787,1],"ix":3},"o":{"a":0,"k":100,"ix":4},"w":{"a":0,"k":0.5,"ix":5},"lc":1,"lj":1,"ml":4,"bm":0,"nm":"Stroke 1","mn":"ADBE Vector Graphic - Stroke","hd":false},{"ty":"fl","c":{"a":0,"k":[0.32549020648,0.345098048449,0.403921574354,1],"ix":4},"o":{"a":0,"k":100,"ix":5},"r":1,"bm":0,"nm":"Fill 1","mn":"ADBE Vector Graphic - Fill","hd":false},{"ty":"tr","p":{"a":0,"k":[0,0],"ix":2},"a":{"a":0,"k":[0,0],"ix":1},"s":{"a":0,"k":[100,100],"ix":3},"r":{"a":0,"k":0,"ix":6},"o":{"a":0,"k":100,"ix":7},"sk":{"a":0,"k":0,"ix":4},"sa":{"a":0,"k":0,"ix":5},"nm":"Transform"}],"nm":"Rectangle 9336","np":3,"cix":2,"bm":0,"ix":1,"mn":"ADBE Vector Group","hd":false}],"ip":33,"op":183,"st":33,"bm":0},{"ddd":0,"ind":5,"ty":4,"nm":"label07","sr":1,"ks":{"o":{"a":0,"k":100,"ix":11},"r":{"a":0,"k":0,"ix":10},"p":{"a":0,"k":[544,321,0],"ix":2,"l":2},"a":{"a":0,"k":[0,0,0],"ix":1,"l":2},"s":{"a":0,"k":[100,100,100],"ix":6,"l":2}},"ao":0,"shapes":[{"ty":"gr","it":[{"ty":"rc","d":1,"s":{"a":0,"k":[58,22],"ix":2},"p":{"a":0,"k":[0,0],"ix":3},"r":{"a":0,"k":1,"ix":4},"nm":"Rectangle Path 1","mn":"ADBE Vector Shape - Rect","hd":false},{"ty":"st","c":{"a":0,"k":[0.435294121504,0.450980395079,0.509803950787,1],"ix":3},"o":{"a":0,"k":100,"ix":4},"w":{"a":0,"k":0.5,"ix":5},"lc":1,"lj":1,"ml":4,"bm":0,"nm":"Stroke 1","mn":"ADBE Vector Graphic - Stroke","hd":false},{"ty":"fl","c":{"a":0,"k":[0.32549020648,0.345098048449,0.403921574354,1],"ix":4},"o":{"a":0,"k":100,"ix":5},"r":1,"bm":0,"nm":"Fill 1","mn":"ADBE Vector Graphic - Fill","hd":false},{"ty":"tr","p":{"a":0,"k":[0,0],"ix":2},"a":{"a":0,"k":[0,0],"ix":1},"s":{"a":0,"k":[100,100],"ix":3},"r":{"a":0,"k":0,"ix":6},"o":{"a":0,"k":100,"ix":7},"sk":{"a":0,"k":0,"ix":4},"sa":{"a":0,"k":0,"ix":5},"nm":"Transform"}],"nm":"Rectangle 9334","np":3,"cix":2,"bm":0,"ix":1,"mn":"ADBE Vector Group","hd":false}],"ip":33,"op":183,"st":33,"bm":0},{"ddd":0,"ind":6,"ty":4,"nm":"label1","sr":1,"ks":{"o":{"a":0,"k":70,"ix":11},"r":{"a":0,"k":0,"ix":10},"p":{"a":1,"k":[{"i":{"x":0.833,"y":0.833},"o":{"x":0.333,"y":0},"t":0,"s":[608,319,0],"to":[-38.833,0,0],"ti":[38.833,0,0]},{"i":{"x":0.833,"y":0.833},"o":{"x":0.333,"y":0.333},"t":9,"s":[375,319,0],"to":[0,0,0],"ti":[0,0,0]},{"i":{"x":0.833,"y":0.833},"o":{"x":0.333,"y":0},"t":21,"s":[375,319,0],"to":[-20.5,0.333,0],"ti":[20.5,-0.333,0]},{"t":33,"s":[252,321,0]}],"ix":2,"l":2},"a":{"a":0,"k":[0,0,0],"ix":1,"l":2},"s":{"a":0,"k":[100,100,100],"ix":6,"l":2}},"ao":0,"shapes":[{"ty":"gr","it":[{"ty":"rc","d":1,"s":{"a":0,"k":[58,22],"ix":2},"p":{"a":0,"k":[0,0],"ix":3},"r":{"a":0,"k":1,"ix":4},"nm":"Rectangle Path 1","mn":"ADBE Vector Shape - Rect","hd":false},{"ty":"st","c":{"a":0,"k":[0.564705908298,0.454901963472,0.741176486015,1],"ix":3},"o":{"a":0,"k":100,"ix":4},"w":{"a":0,"k":0.5,"ix":5},"lc":1,"lj":1,"ml":4,"bm":0,"nm":"Stroke 1","mn":"ADBE Vector Graphic - Stroke","hd":false},{"ty":"fl","c":{"a":0,"k":[0.482352942228,0.349019616842,0.686274528503,1],"ix":4},"o":{"a":0,"k":100,"ix":5},"r":1,"bm":0,"nm":"Fill 1","mn":"ADBE Vector Graphic - Fill","hd":false},{"ty":"tr","p":{"a":0,"k":[0,0],"ix":2},"a":{"a":0,"k":[0,0],"ix":1},"s":{"a":0,"k":[100,100],"ix":3},"r":{"a":0,"k":0,"ix":6},"o":{"a":0,"k":100,"ix":7},"sk":{"a":0,"k":0,"ix":4},"sa":{"a":0,"k":0,"ix":5},"nm":"Transform"}],"nm":"Rectangle 931","np":3,"cix":2,"bm":0,"ix":1,"mn":"ADBE Vector Group","hd":false}],"ip":0,"op":150,"st":0,"bm":0},{"ddd":0,"ind":7,"ty":4,"nm":"label2","sr":1,"ks":{"o":{"a":0,"k":70,"ix":11},"r":{"a":0,"k":0,"ix":10},"p":{"a":1,"k":[{"i":{"x":0.833,"y":0.833},"o":{"x":0.333,"y":0},"t":0,"s":[608,353,0],"to":[-38.833,0,0],"ti":[38.833,0,0]},{"i":{"x":0.833,"y":0.833},"o":{"x":0.333,"y":0.333},"t":9,"s":[375,353,0],"to":[0,0,0],"ti":[0,0,0]},{"i":{"x":0.833,"y":0.833},"o":{"x":0.333,"y":0},"t":21,"s":[375,353,0],"to":[-32.667,-28.333,0],"ti":[32.667,28.333,0]},{"t":33,"s":[179,183,0]}],"ix":2,"l":2},"a":{"a":0,"k":[0,0,0],"ix":1,"l":2},"s":{"a":0,"k":[100,100,100],"ix":6,"l":2}},"ao":0,"shapes":[{"ty":"gr","it":[{"ty":"rc","d":1,"s":{"a":0,"k":[58,22],"ix":2},"p":{"a":0,"k":[0,0],"ix":3},"r":{"a":0,"k":1,"ix":4},"nm":"Rectangle Path 1","mn":"ADBE Vector Shape - Rect","hd":false},{"ty":"st","c":{"a":0,"k":[0.447058826685,0.564705908298,0.800000011921,1],"ix":3},"o":{"a":0,"k":100,"ix":4},"w":{"a":0,"k":0.5,"ix":5},"lc":1,"lj":1,"ml":4,"bm":0,"nm":"Stroke 1","mn":"ADBE Vector Graphic - Stroke","hd":false},{"ty":"fl","c":{"a":0,"k":[0.341176480055,0.482352942228,0.75686275959,1],"ix":4},"o":{"a":0,"k":100,"ix":5},"r":1,"bm":0,"nm":"Fill 1","mn":"ADBE Vector Graphic - Fill","hd":false},{"ty":"tr","p":{"a":0,"k":[0,0],"ix":2},"a":{"a":0,"k":[0,0],"ix":1},"s":{"a":0,"k":[100,100],"ix":3},"r":{"a":0,"k":0,"ix":6},"o":{"a":0,"k":100,"ix":7},"sk":{"a":0,"k":0,"ix":4},"sa":{"a":0,"k":0,"ix":5},"nm":"Transform"}],"nm":"Rectangle 932","np":3,"cix":2,"bm":0,"ix":1,"mn":"ADBE Vector Group","hd":false}],"ip":0,"op":150,"st":0,"bm":0},{"ddd":0,"ind":8,"ty":4,"nm":"label3","sr":1,"ks":{"o":{"a":0,"k":70,"ix":11},"r":{"a":0,"k":0,"ix":10},"p":{"a":1,"k":[{"i":{"x":0.833,"y":0.833},"o":{"x":0.333,"y":0},"t":0,"s":[608,387,0],"to":[-38.833,0,0],"ti":[38.833,0,0]},{"i":{"x":0.833,"y":0.833},"o":{"x":0.333,"y":0.333},"t":9,"s":[375,387,0],"to":[0,0,0],"ti":[0,0,0]},{"i":{"x":0.833,"y":0.833},"o":{"x":0.333,"y":0},"t":21,"s":[375,387,0],"to":[-8.333,-34,0],"ti":[8.333,34,0]},{"t":33,"s":[325,183,0]}],"ix":2,"l":2},"a":{"a":0,"k":[0,0,0],"ix":1,"l":2},"s":{"a":0,"k":[100,100,100],"ix":6,"l":2}},"ao":0,"shapes":[{"ty":"gr","it":[{"ty":"rc","d":1,"s":{"a":0,"k":[58,22],"ix":2},"p":{"a":0,"k":[0,0],"ix":3},"r":{"a":0,"k":1,"ix":4},"nm":"Rectangle Path 1","mn":"ADBE Vector Shape - Rect","hd":false},{"ty":"st","c":{"a":0,"k":[0.729411780834,0.643137276173,0.435294121504,1],"ix":3},"o":{"a":0,"k":100,"ix":4},"w":{"a":0,"k":0.5,"ix":5},"lc":1,"lj":1,"ml":4,"bm":0,"nm":"Stroke 1","mn":"ADBE Vector Graphic - Stroke","hd":false},{"ty":"fl","c":{"a":0,"k":[0.682352941176,0.576470588235,0.309803921569,1],"ix":4},"o":{"a":0,"k":100,"ix":5},"r":1,"bm":0,"nm":"Fill 1","mn":"ADBE Vector Graphic - Fill","hd":false},{"ty":"tr","p":{"a":0,"k":[0,0],"ix":2},"a":{"a":0,"k":[0,0],"ix":1},"s":{"a":0,"k":[100,100],"ix":3},"r":{"a":0,"k":0,"ix":6},"o":{"a":0,"k":100,"ix":7},"sk":{"a":0,"k":0,"ix":4},"sa":{"a":0,"k":0,"ix":5},"nm":"Transform"}],"nm":"Rectangle 933","np":3,"cix":2,"bm":0,"ix":1,"mn":"ADBE Vector Group","hd":false}],"ip":0,"op":150,"st":0,"bm":0},{"ddd":0,"ind":9,"ty":0,"nm":"1_1","refId":"comp_6","sr":1,"ks":{"o":{"a":1,"k":[{"i":{"x":[0.833],"y":[0.833]},"o":{"x":[0.167],"y":[0.167]},"t":22,"s":[100]},{"t":30,"s":[0]}],"ix":11},"r":{"a":0,"k":0,"ix":10},"p":{"a":0,"k":[286.5,242.5,0],"ix":2,"l":2},"a":{"a":0,"k":[286.5,242.5,0],"ix":1,"l":2},"s":{"a":0,"k":[100,100,100],"ix":6,"l":2}},"ao":0,"w":573,"h":485,"ip":0,"op":150,"st":0,"bm":0},{"ddd":0,"ind":10,"ty":4,"nm":"Shape Layer 1","sr":1,"ks":{"o":{"a":0,"k":100,"ix":11},"r":{"a":0,"k":0,"ix":10},"p":{"a":0,"k":[286.5,242.5,0],"ix":2,"l":2},"a":{"a":0,"k":[0,0,0],"ix":1,"l":2},"s":{"a":0,"k":[100,100,100],"ix":6,"l":2}},"ao":0,"shapes":[{"ty":"gr","it":[{"ty":"rc","d":1,"s":{"a":0,"k":[749.734,577.82],"ix":2},"p":{"a":0,"k":[0,0],"ix":3},"r":{"a":0,"k":0,"ix":4},"nm":"Rectangle Path 1","mn":"ADBE Vector Shape - Rect","hd":false},{"ty":"fl","c":{"a":0,"k":[0.105882352941,0.113725490196,0.129411764706,1],"ix":4},"o":{"a":0,"k":100,"ix":5},"r":1,"bm":0,"nm":"Fill 1","mn":"ADBE Vector Graphic - Fill","hd":false},{"ty":"tr","p":{"a":0,"k":[-23.633,-7.59],"ix":2},"a":{"a":0,"k":[0,0],"ix":1},"s":{"a":0,"k":[100,100],"ix":3},"r":{"a":0,"k":0,"ix":6},"o":{"a":0,"k":100,"ix":7},"sk":{"a":0,"k":0,"ix":4},"sa":{"a":0,"k":0,"ix":5},"nm":"Transform"}],"nm":"Rectangle 1","np":3,"cix":2,"bm":0,"ix":1,"mn":"ADBE Vector Group","hd":false}],"ip":0,"op":150,"st":0,"bm":0}],"markers":[]}